mpddrp/main.py
mpddrp/parsing.py
mpddrp/termcolors.py
mpddrp-1.1.1.dist-info/LICENSE
mpddrp-1.1.1.dist-info/METADATA
mpddrp-1.1.1.dist-info/WHEEL
mpddrp-1.1.1.dist-info/entry_points.txt
mpddrp-1.1.1.dist-info/top_level.txt
mpddrp-1.1.1.dist-info/RECORD
