Metadata-Version: 2.1
Name: mpddrp
Version: 1.1.1
Summary: MPD Discord Rich Presence
Home-page: https://github.com/AKurushimi/mpddrp
Author: Franz Łotocki
Author-email: flotocki002@gmail.com
License: UNKNOWN
Platform: UNKNOWN
Classifier: Programming Language :: Python :: 3
Classifier: Programming Language :: Python :: 3.6
Classifier: Programming Language :: Python :: 3.7
Classifier: Programming Language :: Python :: 3.8
Classifier: Programming Language :: Python :: 3.9
Classifier: License :: OSI Approved :: GNU General Public License v3 (GPLv3)
Classifier: Operating System :: OS Independent
Classifier: Intended Audience :: End Users/Desktop
Requires-Python: >=3.6
License-File: LICENSE
Requires-Dist: python-mpd2
Requires-Dist: pypresence
Requires-Dist: colorama
